splitpy
