Metadata-Version: 2.4
Name: SuppsPlit
Version: 0.0.3
Summary: A data splitting based on support points.
Home-page: https://github.com/PanyiDong/SuppsPlit
Author: Panyi Dong
Author-email: panyid2@illinois.edu
Classifier: Programming Language :: Python :: 3
Classifier: Programming Language :: C++
Classifier: License :: OSI Approved :: MIT License
Classifier: Operating System :: OS Independent
Requires-Python: >=3.6
Requires-Dist: pybind11
Requires-Dist: nanoflann
Requires-Dist: numpy
Requires-Dist: pandas
Requires-Dist: scikit-learn
Dynamic: author
Dynamic: author-email
Dynamic: classifier
Dynamic: description
Dynamic: description-content-type
Dynamic: home-page
Dynamic: requires-dist
Dynamic: requires-python
Dynamic: summary
